pymavswarm/__init__.py
pymavswarm/agent.py
pymavswarm/connection.py
pymavswarm/mavswarm.py
pymavswarm/handlers/__init__.py
pymavswarm/handlers/message_receivers.py
pymavswarm/handlers/receivers.py
pymavswarm/message/__init__.py
pymavswarm/message/codes.py
pymavswarm/message/response.py
pymavswarm/mission/__init__.py
pymavswarm/mission/swarm_mission.py
pymavswarm/mission/waypoint.py
pymavswarm/safety/__init__.py
pymavswarm/safety/hyperrectangle.py
pymavswarm/safety/interval.py
pymavswarm/safety/safety_checker.py
pymavswarm/state/__init__.py
pymavswarm/state/acceleration.py
pymavswarm/state/attitude.py
pymavswarm/state/battery.py
pymavswarm/state/docker_info.py
pymavswarm/state/ekf_status.py
pymavswarm/state/generic.py
pymavswarm/state/gps_info.py
pymavswarm/state/parameter.py
pymavswarm/state/parameter_list.py
pymavswarm/state/position.py
pymavswarm/state/state.py
pymavswarm/state/telemetry.py
pymavswarm/state/vector.py
pymavswarm/state/velocity.py
pymavswarm/tests/__init__.py
pymavswarm/tests/test_agent.py
pymavswarm/tests/test_event.py
pymavswarm/tests/test_generic.py
pymavswarm/tests/test_hyperrectangle.py
pymavswarm/tests/test_mission.py
pymavswarm/tests/test_notifier_dict.py
pymavswarm/tests/test_receivers.py
pymavswarm/tests/test_safety_checker.py
pymavswarm/tests/test_state.py
pymavswarm/tests/test_types.py
pymavswarm/types/__init__.py
pymavswarm/utils/__init__.py
pymavswarm/utils/event.py
pymavswarm/utils/logging.py
pymavswarm/utils/notifier_dict.py
pymavswarm-1.2.0.dist-info/LICENSE
pymavswarm-1.2.0.dist-info/METADATA
pymavswarm-1.2.0.dist-info/WHEEL
pymavswarm-1.2.0.dist-info/top_level.txt
pymavswarm-1.2.0.dist-info/zip-safe
pymavswarm-1.2.0.dist-info/RECORD
