Metadata-Version: 2.1
Name: pymavswarm
Version: 1.2.0
Summary: Python library used to communicate with multiple UAS simultaneously using MAVLink
Home-page: https://github.com/unl-nimbus-lab/pymavswarm
Author: Evan Palmer
Author-email: evanp922@gmail.com
License: GPLv3
Project-URL: Source, https://github.com/unl-nimbus-lab/pymavswarm
Platform: any
Classifier: Development Status :: 3 - Alpha
Classifier: Intended Audience :: Science/Research
Classifier: License :: OSI Approved :: GNU General Public License v3 (GPLv3)
Classifier: Operating System :: OS Independent
Classifier: Programming Language :: Python
Classifier: Topic :: Scientific/Engineering
Requires-Python: >=3.10
License-File: LICENSE
Requires-Dist: pymavlink (>=2.3.3)
Requires-Dist: monotonic (>=1.6)
Requires-Dist: pyserial (>=3.0)
Requires-Dist: pandas (>=1.4.3)
Requires-Dist: numpy (>=1.23.1)
Requires-Dist: PyYAML (>=6.0)
